napari_em_reader/__init__.py
napari_em_reader/_reader.py
napari_em_reader/_version.py
napari_em_reader/_tests/__init__.py
napari_em_reader/_tests/test_reader.py
napari_em_reader-0.1.0.dist-info/LICENSE
napari_em_reader-0.1.0.dist-info/METADATA
napari_em_reader-0.1.0.dist-info/WHEEL
napari_em_reader-0.1.0.dist-info/entry_points.txt
napari_em_reader-0.1.0.dist-info/top_level.txt
napari_em_reader-0.1.0.dist-info/RECORD
